commented_code/commented_code.py
commented_code-0.1.0.dist-info/LICENSE
commented_code-0.1.0.dist-info/METADATA
commented_code-0.1.0.dist-info/WHEEL
commented_code-0.1.0.dist-info/top_level.txt
commented_code-0.1.0.dist-info/RECORD
